cebtp/__init__.py
cebtp/preprocessing.py
cebtp/utils.py
cebtp-0.1.2.dist-info/LICENSE
cebtp-0.1.2.dist-info/METADATA
cebtp-0.1.2.dist-info/WHEEL
cebtp-0.1.2.dist-info/top_level.txt
cebtp-0.1.2.dist-info/RECORD
